LICENSE.txt
MANIFEST.in
README.rst
setup.py
demo/demo_common.py
demo/demo_csv.py
demo/demo_data.py
demo/demo_date.py
demo/demo_file.py
demo/demo_logger.py
demo/demo_random.py
demo/demo_system.py
demo/test_conf.ini
demo/conf/test_conf.ini
demo/csv/test_csv.csv
demo/log/blank.txt
demo/log/fish_test.log
demo/sub_dir/demo.txt
docs/__init__.py
docs/conf.py
fishbase/__init__.py
fishbase/fish_common.py
fishbase/fish_crypt.py
fishbase/fish_csv.py
fishbase/fish_data.py
fishbase/fish_date.py
fishbase/fish_file.py
fishbase/fish_http_status.py
fishbase/fish_logger.py
fishbase/fish_object.py
fishbase/fish_project.py
fishbase/fish_random.py
fishbase/fish_system.py
fishbase/fish_token.py
fishbase/fish_validator.py
fishbase.egg-info/PKG-INFO
fishbase.egg-info/SOURCES.txt
fishbase.egg-info/dependency_links.txt
fishbase.egg-info/requires.txt
fishbase.egg-info/top_level.txt
fishbase/db/bankname.csv
fishbase/db/fish_data.sqlite
test/__init__.py
test/test_common.py
test/test_crypt.py
test/test_csv.py
test/test_data.py
test/test_date.py
test/test_file.py
test/test_http_status.py
test/test_logger.py
test/test_object.py
test/test_project.py
test/test_random.py
test/test_system.py